Metadata-Version: 2.1
Name: w2j
Version: 0.4
Summary: A tool for migrating from WizNote to Joplin.
Home-page: https://github.com/zrong/wiz2joplin
Author: zrong
Author-email: zrongzrong@gmail.com
License: GPLv3
Keywords: development zrong wiznote joplin
Platform: UNKNOWN
Classifier: Programming Language :: Python :: 3.9
Classifier: Development Status :: 4 - Beta
Classifier: Environment :: Console
Classifier: Topic :: System :: Shells
Classifier: Topic :: Utilities
Classifier: Topic :: Text Processing :: Markup :: HTML
Classifier: Topic :: Text Processing :: Markup :: Markdown
Classifier: License :: OSI Approved :: GNU General Public License v3 (GPLv3)
Requires-Python: >=3.9, <4
